yamlconf/config.py
yamlconf/const.py
yamlconf/utils.py
yamlconf_kei-0.0.1.dist-info/METADATA
yamlconf_kei-0.0.1.dist-info/WHEEL
yamlconf_kei-0.0.1.dist-info/top_level.txt
yamlconf_kei-0.0.1.dist-info/RECORD
